{
  "annoy": {
    "dataset": "sift1m",
    "method": "annoy",
    "k": 10,
    "n_queries": 200,
    "n_train": 1000000,
    "n_dims": 128,
    "random_seed": 42,
    "method_params": {
      "tolerance": 49.5,
      "confidence": 0.99,
      "max_cv": null,
      "block_size": 256,
      "n_components": 32,
      "n_clusters": 100,
      "n_tables": 10,
      "n_trees": 10,
      "ef": 10
    },
    "build_time": 6.302186376880854,
    "mean_exact_time": 0.2873605888453312,
    "metrics": {
      "recall": {
        "mean": 0.244,
        "std": 0.22861321046693692,
        "min": 0.0,
        "max": 1.0,
        "median": 0.2,
        "p10": 0.0,
        "p25": 0.1,
        "p75": 0.4,
        "p90": 0.6,
        "ci_lower": 0.21204254952159257,
        "ci_upper": 0.2759574504784074
      },
      "speedup": {
        "mean": 5474.968868534875,
        "std": 937.3702126577133,
        "min": 1125.6510468919298,
        "max": 8307.11258682659,
        "median": 5489.541911339271,
        "p10": 4525.15137092739,
        "p25": 4949.03176419089,
        "p75": 6002.0590213013,
        "p90": 6434.408832833583,
        "ci_lower": 5343.935486475462,
        "ci_upper": 5606.002250594287
      },
      "dist_ratio": {
        "mean": 0.0001,
        "std": 0.0
      },
      "failure_rate_95": 0.99,
      "failure_rate_99": 0.99,
      "scan_ratio": {
        "mean": 0.00010000000000000002,
        "std": 1.3552527156068805e-20
      }
    },
    "per_query": {
      "recalls": [
        0.5,
        0.1,
        0.3,
        0.1,
        0.1,
        0.5,
        0.0,
        0.4,
        0.1,
        0.2,
        0.0,
        0.2,
        0.0,
        0.2,
        0.0,
        0.2,
        0.2,
        0.2,
        0.0,
        0.2,
        0.4,
        0.8,
        0.2,
        0.2,
        0.6,
        0.3,
        0.7,
        0.6,
        0.3,
        0.1,
        0.1,
        0.3,
        0.3,
        0.9,
        0.6,
        0.1,
        0.0,
        0.2,
        0.1,
        0.4,
        0.2,
        0.4,
        0.1,
        0.6,
        0.1,
        0.5,
        0.4,
        0.2,
        0.1,
        0.0,
        0.3,
        0.3,
        0.1,
        0.0,
        0.4,
        0.1,
        0.0,
        0.9,
        0.3,
        0.0,
        0.1,
        0.0,
        0.3,
        0.5,
        0.2,
        0.4,
        0.7,
        0.4,
        0.2,
        0.2,
        0.9,
        0.4,
        0.0,
        0.4,
        0.5,
        0.1,
        0.7,
        1.0,
        0.1,
        0.0,
        0.0,
        0.3,
        0.0,
        0.0,
        0.4,
        0.3,
        0.4,
        0.0,
        0.1,
        0.4,
        0.2,
        0.0,
        0.5,
        0.3,
        0.3,
        0.0,
        0.1,
        1.0,
        0.2,
        0.1,
        0.3,
        0.1,
        0.2,
        0.0,
        0.1,
        0.0,
        0.4,
        0.5,
        0.1,
        0.3,
        0.0,
        0.4,
        0.5,
        0.3,
        0.8,
        0.1,
        0.0,
        0.8,
        0.1,
        0.0,
        0.2,
        0.1,
        0.2,
        0.1,
        0.1,
        0.4,
        0.0,
        0.4,
        0.2,
        0.3,
        0.4,
        0.0,
        0.4,
        0.8,
        0.1,
        0.3,
        0.3,
        0.2,
        0.0,
        0.2,
        0.6,
        0.3,
        0.3,
        0.4,
        0.2,
        0.2,
        0.1,
        0.4,
        0.1,
        0.2,
        0.6,
        0.0,
        0.4,
        0.5,
        0.1,
        0.1,
        0.1,
        0.2,
        0.0,
        0.0,
        0.2,
        0.3,
        0.7,
        0.0,
        0.3,
        0.0,
        0.1,
        0.1,
        0.7,
        0.0,
        0.1,
        0.0,
        0.0,
        0.0,
        0.3,
        0.0,
        0.1,
        0.3,
        0.4,
        0.2,
        0.2,
        0.1,
        0.0,
        0.2,
        0.4,
        0.0,
        0.5,
        0.6,
        0.1,
        0.2,
        0.1,
        0.2,
        0.2,
        0.0,
        0.0,
        0.0,
        0.2,
        0.0,
        0.1,
        0.0
      ],
      "speedups": [
        2457.145109318882,
        4365.990290463624,
        2680.756767572992,
        4347.014409868977,
        4000.740148106608,
        4735.21098222096,
        4567.168939696708,
        4093.356631035375,
        4607.647021765101,
        4333.6739230812445,
        4410.26675641777,
        4537.916328095126,
        5177.205322535991,
        5110.196056815641,
        8307.11258682659,
        4346.769452447031,
        4679.554155734349,
        4776.0368214429445,
        5685.376772355402,
        4132.611187845304,
        4184.112264979286,
        5533.109465923661,
        4840.092908320131,
        4692.185539702092,
        4380.681098218913,
        5543.896126428417,
        5344.3565803945685,
        4851.927992837318,
        4784.553688419731,
        4708.439190503804,
        4760.231767358085,
        4557.589424191845,
        4573.5663881848095,
        4818.738945870392,
        4822.316248007314,
        6276.530127696579,
        5354.09399456003,
        5152.307430993888,
        5979.961874364068,
        4987.409608064203,
        6461.735119265767,
        1125.6510468919298,
        1316.7318144526332,
        2652.2521742073573,
        5295.01446342154,
        6232.473848395176,
        4358.096918940106,
        5921.205976117599,
        3615.1904580924092,
        4572.143184596577,
        4799.8488385433275,
        4710.272079084359,
        5157.992022943831,
        5576.761907397701,
        5252.0227205995,
        4086.2010291615074,
        5445.419506949041,
        4829.9026010237385,
        5036.581940068884,
        4374.563435732211,
        5525.628273862822,
        5109.09604358985,
        6135.070145199133,
        5164.5102530358445,
        6322.832873543786,
        4895.499310816707,
        5349.406336956805,
        5607.82753673564,
        5829.527911211245,
        6322.703308623887,
        6033.045896594876,
        5768.118573865495,
        4795.335739346326,
        5121.009805691097,
        5503.698244147157,
        5317.737497414818,
        6359.059031820945,
        4927.238772825627,
        6378.514740767156,
        6637.434154270594,
        5297.787364894448,
        5074.895070066365,
        5942.073561909622,
        6433.508815940367,
        5499.284103061088,
        5349.12812053049,
        5597.501638381438,
        5332.856586543032,
        6242.3719678424395,
        6205.274772996943,
        5751.45314902838,
        7265.9236983551355,
        5835.7022074121005,
        5884.954040348652,
        5426.600587637841,
        5252.514453726795,
        5603.244855084307,
        6364.174347702779,
        4990.11171814984,
        6442.508984872528,
        5981.642843814822,
        7275.689609689095,
        7350.129417387265,
        6300.432540634635,
        5500.9017990854145,
        5990.934174950974,
        6058.1581695512605,
        5851.972135426545,
        5095.764408427676,
        5397.033134439965,
        6308.74148281996,
        5997.571877551219,
        5898.679618274276,
        6181.096844105892,
        6236.000784423695,
        5257.52643769968,
        5433.576635306237,
        5843.7705078125,
        6643.507941014986,
        5958.2524608722515,
        6837.545601482516,
        5560.029963554947,
        4930.388098919009,
        6409.320180563345,
        5259.273928078339,
        6660.501944123646,
        5850.862462312272,
        5354.60502767968,
        5509.447232563745,
        5929.740514706589,
        5840.1757026924715,
        6468.440552871009,
        6305.776091321542,
        5456.397301652563,
        6015.520452551543,
        6318.8188286521745,
        5802.122695283852,
        7001.30660674374,
        5395.004245567562,
        5843.991871140953,
        6166.951468280935,
        6455.178619061068,
        7631.358399596854,
        5841.115455332803,
        5181.291377348827,
        6043.622102332824,
        5427.698365143586,
        4792.468183318449,
        5803.759739908584,
        5736.056492429101,
        5645.84514121425,
        5309.593247737128,
        5789.276747518622,
        4947.18662817265,
        5382.2994891150765,
        6220.599836950495,
        5914.112604701756,
        5366.619116828566,
        5412.179910937459,
        6219.157938695504,
        6171.26850699028,
        5041.684359681372,
        7011.887165087265,
        5929.341689006111,
        5989.829319339966,
        5940.643501270722,
        6818.883806727146,
        5129.054279391597,
        7077.833711347892,
        5391.045232073593,
        5440.091025997038,
        5832.723682655955,
        5875.540713755248,
        4878.046619330308,
        5856.026016806005,
        4358.7741343932985,
        4861.368879982669,
        6560.031525725523,
        5199.977801582487,
        6365.027700563165,
        5468.533803812275,
        4771.051897860727,
        7077.914891268194,
        5501.097948127083,
        5717.720754808762,
        4949.646809530303,
        5479.799719617455,
        5390.150546568606,
        5300.107922435413,
        6052.632170985523,
        5444.50668429736,
        6033.163862003226,
        5430.516435152593,
        5561.98436795854,
        5761.602203658058,
        6379.437892187774,
        5299.42519450909,
        5976.718536624343,
        4700.87119783811,
        7157.7122962941485
      ],
      "dist_counts": [
        100,
        100,
        100,
        100,
        100,
        100,
        100,
        100,
        100,
        100,
        100,
        100,
        100,
        100,
        100,
        100,
        100,
        100,
        100,
        100,
        100,
        100,
        100,
        100,
        100,
        100,
        100,
        100,
        100,
        100,
        100,
        100,
        100,
        100,
        100,
        100,
        100,
        100,
        100,
        100,
        100,
        100,
        100,
        100,
        100,
        100,
        100,
        100,
        100,
        100,
        100,
        100,
        100,
        100,
        100,
        100,
        100,
        100,
        100,
        100,
        100,
        100,
        100,
        100,
        100,
        100,
        100,
        100,
        100,
        100,
        100,
        100,
        100,
        100,
        100,
        100,
        100,
        100,
        100,
        100,
        100,
        100,
        100,
        100,
        100,
        100,
        100,
        100,
        100,
        100,
        100,
        100,
        100,
        100,
        100,
        100,
        100,
        100,
        100,
        100,
        100,
        100,
        100,
        100,
        100,
        100,
        100,
        100,
        100,
        100,
        100,
        100,
        100,
        100,
        100,
        100,
        100,
        100,
        100,
        100,
        100,
        100,
        100,
        100,
        100,
        100,
        100,
        100,
        100,
        100,
        100,
        100,
        100,
        100,
        100,
        100,
        100,
        100,
        100,
        100,
        100,
        100,
        100,
        100,
        100,
        100,
        100,
        100,
        100,
        100,
        100,
        100,
        100,
        100,
        100,
        100,
        100,
        100,
        100,
        100,
        100,
        100,
        100,
        100,
        100,
        100,
        100,
        100,
        100,
        100,
        100,
        100,
        100,
        100,
        100,
        100,
        100,
        100,
        100,
        100,
        100,
        100,
        100,
        100,
        100,
        100,
        100,
        100,
        100,
        100,
        100,
        100,
        100,
        100,
        100,
        100,
        100,
        100,
        100,
        100
      ],
      "query_times": [
        0.00011694896966218948,
        6.581796333193779e-05,
        0.00010719383135437965,
        6.610527634620667e-05,
        7.182685658335686e-05,
        6.0685910284519196e-05,
        6.29187561571598e-05,
        7.020169869065285e-05,
        6.236601620912552e-05,
        6.630877032876015e-05,
        6.515718996524811e-05,
        6.332434713840485e-05,
        5.550496280193329e-05,
        5.6232791393995285e-05,
        3.459211438894272e-05,
        6.610900163650513e-05,
        6.140768527984619e-05,
        6.0167163610458374e-05,
        5.0543807446956635e-05,
        6.953487172722816e-05,
        6.867898628115654e-05,
        5.193473771214485e-05,
        5.937088280916214e-05,
        6.124237552285194e-05,
        6.559723988175392e-05,
        5.183368921279907e-05,
        5.376897752285004e-05,
        5.922606214880943e-05,
        6.0060061514377594e-05,
        6.103096529841423e-05,
        6.0366932302713394e-05,
        6.30510039627552e-05,
        6.283074617385864e-05,
        5.963398143649101e-05,
        5.958974361419678e-05,
        4.5783352106809616e-05,
        5.367118865251541e-05,
        5.5773183703422546e-05,
        4.805391654372215e-05,
        5.7617202401161194e-05,
        4.447111859917641e-05,
        0.0002552838996052742,
        0.0002182377502322197,
        0.000108345877379179,
        5.4270029067993164e-05,
        4.6106986701488495e-05,
        6.593717262148857e-05,
        4.853075370192528e-05,
        7.948698475956917e-05,
        6.285030394792557e-05,
        5.986867472529411e-05,
        6.1007216572761536e-05,
        5.5711716413497925e-05,
        5.1528215408325195e-05,
        5.471426993608475e-05,
        7.032463327050209e-05,
        5.277106538414955e-05,
        5.949614569544792e-05,
        5.7054683566093445e-05,
        6.568897515535355e-05,
        5.200505256652832e-05,
        5.6244898587465286e-05,
        4.683900624513626e-05,
        5.5641401559114456e-05,
        4.5448075979948044e-05,
        5.869893357157707e-05,
        5.371822044253349e-05,
        5.124276503920555e-05,
        4.929397255182266e-05,
        4.544900730252266e-05,
        4.7631096094846725e-05,
        4.9818772822618484e-05,
        5.992501974105835e-05,
        5.611404776573181e-05,
        5.2212271839380264e-05,
        5.403812974691391e-05,
        4.518916830420494e-05,
        5.832081660628319e-05,
        4.505133256316185e-05,
        4.329392686486244e-05,
        5.424162372946739e-05,
        5.6623946875333786e-05,
        4.8360321670770645e-05,
        4.466623067855835e-05,
        5.225418135523796e-05,
        5.372101441025734e-05,
        5.133729428052902e-05,
        5.3884927183389664e-05,
        4.603387787938118e-05,
        4.6309083700180054e-05,
        4.9963127821683884e-05,
        3.95490787923336e-05,
        4.9241818487644196e-05,
        4.8829708248376846e-05,
        5.295407027006149e-05,
        5.470914766192436e-05,
        5.128467455506325e-05,
        4.515284672379494e-05,
        5.7586003094911575e-05,
        4.460383206605911e-05,
        4.804041236639023e-05,
        3.949599340558052e-05,
        3.909599035978317e-05,
        4.560966044664383e-05,
        5.2238814532756805e-05,
        4.796590656042099e-05,
        4.7433655709028244e-05,
        4.910491406917572e-05,
        5.639204755425453e-05,
        5.3244177252054214e-05,
        4.554959014058113e-05,
        4.791282117366791e-05,
        4.871608689427376e-05,
        4.6490225940942764e-05,
        4.608090966939926e-05,
        5.4656993597745895e-05,
        5.288608372211456e-05,
        4.9173831939697266e-05,
        4.3254345655441284e-05,
        4.822900518774986e-05,
        4.2026862502098083e-05,
        5.168328061699867e-05,
        5.828356370329857e-05,
        4.483480006456375e-05,
        5.4638832807540894e-05,
        4.314398393034935e-05,
        4.9114227294921875e-05,
        5.3666066378355026e-05,
        5.215778946876526e-05,
        4.846090450882912e-05,
        4.920409992337227e-05,
        4.442501813173294e-05,
        4.557101055979729e-05,
        5.266489461064339e-05,
        4.776986315846443e-05,
        4.5476946979761124e-05,
        4.952680319547653e-05,
        4.1043851524591446e-05,
        5.326420068740845e-05,
        4.9171969294548035e-05,
        4.6596862375736237e-05,
        4.451628774404526e-05,
        3.765523433685303e-05,
        4.919618368148804e-05,
        5.546119064092636e-05,
        4.754774272441864e-05,
        5.2943360060453415e-05,
        5.9960875660181046e-05,
        4.95128333568573e-05,
        5.009723827242851e-05,
        5.0897710025310516e-05,
        5.412101745605469e-05,
        4.963669925928116e-05,
        5.808565765619278e-05,
        5.338992923498154e-05,
        4.619499668478966e-05,
        4.8588961362838745e-05,
        5.354592576622963e-05,
        5.309516564011574e-05,
        4.6205706894397736e-05,
        4.6564266085624695e-05,
        5.6996941566467285e-05,
        4.0981918573379517e-05,
        4.846416413784027e-05,
        4.797475412487984e-05,
        4.837196320295334e-05,
        4.2141880840063095e-05,
        5.602603778243065e-05,
        4.060007631778717e-05,
        5.33033162355423e-05,
        5.282275378704071e-05,
        4.9266964197158813e-05,
        4.8907939344644547e-05,
        5.890894681215286e-05,
        4.9070920795202255e-05,
        6.59269280731678e-05,
        5.911104381084442e-05,
        4.380475729703903e-05,
        5.526188760995865e-05,
        4.5146793127059937e-05,
        5.2548013627529144e-05,
        6.023002788424492e-05,
        4.059961065649986e-05,
        5.2236951887607574e-05,
        5.025789141654968e-05,
        5.80567866563797e-05,
        5.243998020887375e-05,
        5.3312163800001144e-05,
        5.42178750038147e-05,
        4.7476962208747864e-05,
        5.27799129486084e-05,
        4.763016477227211e-05,
        5.291588604450226e-05,
        5.166511982679367e-05,
        4.987511783838272e-05,
        4.504481330513954e-05,
        5.422485992312431e-05,
        4.8079993575811386e-05,
        6.112921983003616e-05,
        4.014698788523674e-05
      ],
      "scan_ratios": [
        0.0001,
        0.0001,
        0.0001,
        0.0001,
        0.0001,
        0.0001,
        0.0001,
        0.0001,
        0.0001,
        0.0001,
        0.0001,
        0.0001,
        0.0001,
        0.0001,
        0.0001,
        0.0001,
        0.0001,
        0.0001,
        0.0001,
        0.0001,
        0.0001,
        0.0001,
        0.0001,
        0.0001,
        0.0001,
        0.0001,
        0.0001,
        0.0001,
        0.0001,
        0.0001,
        0.0001,
        0.0001,
        0.0001,
        0.0001,
        0.0001,
        0.0001,
        0.0001,
        0.0001,
        0.0001,
        0.0001,
        0.0001,
        0.0001,
        0.0001,
        0.0001,
        0.0001,
        0.0001,
        0.0001,
        0.0001,
        0.0001,
        0.0001,
        0.0001,
        0.0001,
        0.0001,
        0.0001,
        0.0001,
        0.0001,
        0.0001,
        0.0001,
        0.0001,
        0.0001,
        0.0001,
        0.0001,
        0.0001,
        0.0001,
        0.0001,
        0.0001,
        0.0001,
        0.0001,
        0.0001,
        0.0001,
        0.0001,
        0.0001,
        0.0001,
        0.0001,
        0.0001,
        0.0001,
        0.0001,
        0.0001,
        0.0001,
        0.0001,
        0.0001,
        0.0001,
        0.0001,
        0.0001,
        0.0001,
        0.0001,
        0.0001,
        0.0001,
        0.0001,
        0.0001,
        0.0001,
        0.0001,
        0.0001,
        0.0001,
        0.0001,
        0.0001,
        0.0001,
        0.0001,
        0.0001,
        0.0001,
        0.0001,
        0.0001,
        0.0001,
        0.0001,
        0.0001,
        0.0001,
        0.0001,
        0.0001,
        0.0001,
        0.0001,
        0.0001,
        0.0001,
        0.0001,
        0.0001,
        0.0001,
        0.0001,
        0.0001,
        0.0001,
        0.0001,
        0.0001,
        0.0001,
        0.0001,
        0.0001,
        0.0001,
        0.0001,
        0.0001,
        0.0001,
        0.0001,
        0.0001,
        0.0001,
        0.0001,
        0.0001,
        0.0001,
        0.0001,
        0.0001,
        0.0001,
        0.0001,
        0.0001,
        0.0001,
        0.0001,
        0.0001,
        0.0001,
        0.0001,
        0.0001,
        0.0001,
        0.0001,
        0.0001,
        0.0001,
        0.0001,
        0.0001,
        0.0001,
        0.0001,
        0.0001,
        0.0001,
        0.0001,
        0.0001,
        0.0001,
        0.0001,
        0.0001,
        0.0001,
        0.0001,
        0.0001,
        0.0001,
        0.0001,
        0.0001,
        0.0001,
        0.0001,
        0.0001,
        0.0001,
        0.0001,
        0.0001,
        0.0001,
        0.0001,
        0.0001,
        0.0001,
        0.0001,
        0.0001,
        0.0001,
        0.0001,
        0.0001,
        0.0001,
        0.0001,
        0.0001,
        0.0001,
        0.0001,
        0.0001,
        0.0001,
        0.0001,
        0.0001,
        0.0001,
        0.0001,
        0.0001,
        0.0001,
        0.0001,
        0.0001,
        0.0001,
        0.0001,
        0.0001,
        0.0001,
        0.0001
      ]
    }
  }
}